{
  "r1-s3": "원주시 개운동 원주초등학교",
  "r1-s6": "원주시 단구동 단구초등학교",
  "r1-s7": "강원 원주시 치악로 1489 홈플러스 원주점",
  "r2-s1": "봉화산e편한세상아파트",
  "r2-s2": "원주시 단계동 원주시외버스터미널",
  "r2-s3": "원주시 명륜동 원주청소년수련관",
  "r2-s4": "원주시 명륜동 치악체육관",
  "r2-s5": "원주시 명륜동 원주종합운동장",
  "r2-s6": "원주시 단구동 롯데시네마 남원주",
  "r3-s1": "원주시 단구동 치악고등학교",
  "r3-s4": "원주시 관설동 청솔6차아파트",
  "r4-s3": "원주시 단계동 벽산아파트",
  "r4-s4": "원주시 단계동 행정복지센터",
  "r4-s6": "옛원주역 택시승강장",
  "r4-s7": "원주시 중앙동 중앙시장",
  "r4-s8": "원주시 개운동 남부시장",
  "r4-s9": "원주시 개운동 원주고등학교",
  "r4-s10": "원주시 반곡동 반곡아이파크",
  "r5-s4": "원주시 반곡동 봉대초등학교",
  "r6-s2": "원주시 단계동 봉화산푸르지오아파트",
  "r6-s3": "원주시 단계동 원주시외버스터미널",
  "r6-s4": "원주시 명륜동 원주종합운동장",
  "r6-s6": "원주시 단구동 단구초등학교",
  "r6-s7": "강원 원주시 치악로 1489 홈플러스 원주점",
  "r7-s2": "원주시 반곡동 봉대초등학교",
  "r8-s1": "원주시 무실동 무실초등학교",
  "r8-s4": "동보노빌리티2단지아파트",
  "r8-s5": "원주시 무실동 남원주중학교",
  "r8-s6": "구곡현대2차아파트",
  "r9-s1": "원주시 호저면 만종역"
}
